README.md
setup.py
PYSTUDY/__init__.py
PYSTUDY/collectionslib.py
PYSTUDY/debuglib.py
PYSTUDY/encodelib.py
PYSTUDY/encryptlib.py
PYSTUDY/html_parserlib.py
PYSTUDY/jsonlib.py
PYSTUDY/loglib.py
PYSTUDY/modulelib.py
PYSTUDY/numpylib.py
PYSTUDY/oslib.py
PYSTUDY/pprintlib.py
PYSTUDY/processlib.py
PYSTUDY/randomlib.py
PYSTUDY/seleniumlib.py
PYSTUDY/stringlib.py
PYSTUDY/threadinglib.py
PYSTUDY/timelib.py
PYSTUDY/unittestlib.py
PYSTUDY/webbrowserlib.py
PYSTUDY/yamllib.py
PYSTUDY.egg-info/PKG-INFO
PYSTUDY.egg-info/SOURCES.txt
PYSTUDY.egg-info/dependency_links.txt
PYSTUDY.egg-info/requires.txt
PYSTUDY.egg-info/top_level.txt
PYSTUDY/api/__init__.py
PYSTUDY/api/google.py
PYSTUDY/api/gpsspg.py
PYSTUDY/image/__init__.py
PYSTUDY/image/opencvlib.py
PYSTUDY/image/pillib.py
PYSTUDY/middleware/__init__.py
PYSTUDY/middleware/mongolib.py
PYSTUDY/middleware/mysqllib.py
PYSTUDY/middleware/rabbitmqlib.py
PYSTUDY/middleware/redislib.py
PYSTUDY/ml/__init__.py
PYSTUDY/ml/knnlib.py
PYSTUDY/ml/tensorflowlib.py
PYSTUDY/net/__init__.py
PYSTUDY/net/fingerlib.py
PYSTUDY/net/requestslib.py
PYSTUDY/net/scapylib.py
PYSTUDY/net/tornadolib.py
PYSTUDY/office/__init__.py
PYSTUDY/office/csvlib.py
PYSTUDY/office/excellib.py
PYSTUDY/office/pdflib.py