Metadata-Version: 1.1
Name: PYSTUDY
Version: 0.6.0
Summary: learning python
Home-page: https://github.com/shi-cong/PYSTUDY
Author: shi-cong
Author-email: shi_cong@icloud.com
License: Apache License
Platform: UNKNOWN
Classifier: Development Status :: 5 - Production/Stable
Classifier: Intended Audience :: Developers
Classifier: Natural Language :: English
Classifier: License :: OSI Approved :: MIT License
Classifier: Programming Language :: Python :: 3.6
